README
ez_setup.py
setup.py
mainloop/__init__.py
mainloop.egg-info/PKG-INFO
mainloop.egg-info/SOURCES.txt
mainloop.egg-info/dependency_links.txt
mainloop.egg-info/top_level.txt
