Metadata-Version: 1.0
Name: mainloop
Version: 2
Summary: A class which provides a fixed duration simulation loop with frame skipping when needed.
Home-page: http://code.google.com/p/corsair-redux/wiki/mainloop
Author: Simon Wittber
Author-email: simonwittber@gmail.com
License: MIT
Platform: Any
